{
  "title": "[賣/桃園/面交、郵寄] AMD r5-2600, D4 -16GB",
  "url": "https://www.ptt.cc/bbs/HardwareSale/M.1762323361.A.6E5.html"
}{
  "title": "[徵/台北/皆可］Tp-link deco x20 * 3",
  "url": "https://www.ptt.cc/bbs/HardwareSale/M.1762324160.A.590.html"
}{
  "title": "[賣/全國/皆可] HP HyperX PH 2 Mini 洽中",
  "url": "https://www.ptt.cc/bbs/HardwareSale/M.1762325447.A.7C9.html"
}{
  "title": "[賣/全國/面交] i7-8700主機，微星GTX-1080",
  "url": "https://www.ptt.cc/bbs/HardwareSale/M.1762326553.A.AE8.html"
}{
  "title": "[賣/台中/皆可] RTX 3070",
  "url": "https://www.ptt.cc/bbs/HardwareSale/M.1762327360.A.5E1.html"
}{
  "title": "[徵/三重/皆可]  徵 1660s二手",
  "url": "https://www.ptt.cc/bbs/HardwareSale/M.1762328436.A.7CB.html"
}{
  "title": "[賣/台北/面交] Dell S2721h螢幕",
  "url": "https://www.ptt.cc/bbs/HardwareSale/M.1762330623.A.B4A.html"
}{
  "title": "[賣/台中/面交]XPG DDR5 6400 32G*2 RGB黑 ",
  "url": "https://www.ptt.cc/bbs/HardwareSale/M.1762333643.A.98A.html"
}{
  "title": "[賣/高雄/皆可] i7-7700/i7-11700/i5-8400半套",
  "url": "https://www.ptt.cc/bbs/HardwareSale/M.1762334925.A.8FD.html"
}{
  "title": "[賣/雙北/面交]AMD R5 3500X ",
  "url": "https://www.ptt.cc/bbs/HardwareSale/M.1762336091.A.9BD.html"
}{
  "title": "[徵/雲林/皆可] A320/B350/B450/A520主板",
  "url": "https://www.ptt.cc/bbs/HardwareSale/M.1762245729.A.850.html"
}{
  "title": "[賣/台北/面交] 5600X+3070ti主機",
  "url": "https://www.ptt.cc/bbs/HardwareSale/M.1762255689.A.E83.html"
}{
  "title": "[賣/台北/皆可] KIOXIA EXCERIA PLUS 外接SSD 1T ",
  "url": "https://www.ptt.cc/bbs/HardwareSale/M.1762256527.A.B21.html"
}{
  "title": "[賣/高雄/面交] 8700半套/EVGA3060/銀欣750W",
  "url": "https://www.ptt.cc/bbs/HardwareSale/M.1762258006.A.6D0.html"
}{
  "title": "[賣/三重/皆可]AMD 5600G/B550M/16G (售出)",
  "url": "https://www.ptt.cc/bbs/HardwareSale/M.1762262433.A.B3E.html"
}{
  "title": "[賣/台中/皆可] 暫售)羅技 Keys-to-go2 便攜鍵盤",
  "url": "https://www.ptt.cc/bbs/HardwareSale/M.1762265925.A.885.html"
}{
  "title": "[賣/雙北/面交]電供(記憶體和顯卡賣出)",
  "url": "https://www.ptt.cc/bbs/HardwareSale/M.1762275931.A.081.html"
}{
  "title": "[徵/全國/寄送] AMD Ryzen 7 PRO 4750G (洽中)",
  "url": "https://www.ptt.cc/bbs/HardwareSale/M.1762282299.A.E86.html"
}{
  "title": "[賣/台北/皆可] 鍵盤 3M螢幕防窺片",
  "url": "https://www.ptt.cc/bbs/HardwareSale/M.1762304578.A.6E1.html"
}{
  "title": "[徵/全國/寄送] AMD Ryzen 3 PRO 4350G",
  "url": "https://www.ptt.cc/bbs/HardwareSale/M.1762306436.A.0F2.html"
}{
  "title": "[徵/全國/寄送] 主機板及CPU 效能約11400",
  "url": "https://www.ptt.cc/bbs/HardwareSale/M.1762307222.A.24D.html"
}{
  "title": "[賣/雙北/皆可] (售出)Samsung 860evo 500g ",
  "url": "https://www.ptt.cc/bbs/HardwareSale/M.1762310634.A.6C1.html"
}{
  "title": "[徵/全國/皆可] 小米ax3000t",
  "url": "https://www.ptt.cc/bbs/HardwareSale/M.1762310860.A.E42.html"
}{
  "title": "[賣/全國/寄送]桌機記憶體、原廠風扇",
  "url": "https://www.ptt.cc/bbs/HardwareSale/M.1762311058.A.58C.html"
}{
  "title": "[徵/台北/面交] TP-Link Archer MR600  分享器",
  "url": "https://www.ptt.cc/bbs/HardwareSale/M.1762313568.A.C74.html"
}{
  "title": "[徵/高雄/面交] 27-32吋螢幕(FHD/2K皆可) / A380",
  "url": "https://www.ptt.cc/bbs/HardwareSale/M.1762314553.A.E7D.html"
}{
  "title": "[賣/彰化/台中面交］9070xt",
  "url": "https://www.ptt.cc/bbs/HardwareSale/M.1762314587.A.7A8.html"
}{
  "title": "[賣/全國/賣貨便] 鎌刀 SCBSK-4000 大手裏劍4下吹",
  "url": "https://www.ptt.cc/bbs/HardwareSale/M.1762321340.A.34E.html"
}{
  "title": "[賣/雙北/皆可]Netgear R7000 無線路由器",
  "url": "https://www.ptt.cc/bbs/HardwareSale/M.1762322487.A.E83.html"
}{
  "title": "[徵/台中/面交] RTX3060Ti RTX4060 ",
  "url": "https://www.ptt.cc/bbs/HardwareSale/M.1762189583.A.658.html"
}{
  "title": "[賣/新北/自取] 羅技G213鍵盤 Corsair A50散熱器",
  "url": "https://www.ptt.cc/bbs/HardwareSale/M.1762201229.A.844.html"
}{
  "title": "[賣/彰化、台中/面交]紅米AX6分享器兩台",
  "url": "https://www.ptt.cc/bbs/HardwareSale/M.1762219959.A.9A1.html"
}{
  "title": "[徵/台北/面交] 24吋 螢幕  FHD +  ",
  "url": "https://www.ptt.cc/bbs/HardwareSale/M.1762221617.A.819.html"
}{
  "title": "[徵/雙北/皆可] 3080ti/3080/3070ti",
  "url": "https://www.ptt.cc/bbs/HardwareSale/M.1762222560.A.E43.html"
}{
  "title": "[徵/中部/面交]RTX 4070Ti Super /RTX 4080",
  "url": "https://www.ptt.cc/bbs/HardwareSale/M.1762226654.A.CA8.html"
}{
  "title": "[賣/台北/面交] RX6650XT, RX560, ROG550W ",
  "url": "https://www.ptt.cc/bbs/HardwareSale/M.1762226982.A.5CC.html"
}{
  "title": "[賣/全國/寄送] 羅技 MX Keys Combo 無線鍵鼠組",
  "url": "https://www.ptt.cc/bbs/HardwareSale/M.1762226987.A.274.html"
}{
  "title": "[徵/中壢/面交] rx6600~6700 xt系列顯卡",
  "url": "https://www.ptt.cc/bbs/HardwareSale/M.1762230437.A.9ED.html"
}{
  "title": "[徵/台北/面交] AMD7700 or 7500F半套",
  "url": "https://www.ptt.cc/bbs/HardwareSale/M.1762232893.A.5B6.html"
}{
  "title": "[賣/桃園/面交]ASUS Dual RTX 4070 Super 12G",
  "url": "https://www.ptt.cc/bbs/HardwareSale/M.1762234095.A.95E.html"
}{
  "title": "[賣/全國/皆可] R3-5300GE、A320M-ITX、DDR4 16G",
  "url": "https://www.ptt.cc/bbs/HardwareSale/M.1762235206.A.A05.html"
}{
  "title": "[徵/雙北/面交] Intel CPU i5 12500 ",
  "url": "https://www.ptt.cc/bbs/HardwareSale/M.1762235412.A.963.html"
}{
  "title": "[徵/中部/面交] 全套主機",
  "url": "https://www.ptt.cc/bbs/HardwareSale/M.1762236440.A.6E4.html"
}{
  "title": "[徵/全國/皆可] AMD AM4 處理器CPU",
  "url": "https://www.ptt.cc/bbs/HardwareSale/M.1762238476.A.D73.html"
}{
  "title": "[徵/雙北/面交] 佛系徵32吋曲面螢幕",
  "url": "https://www.ptt.cc/bbs/HardwareSale/M.1762239440.A.BA8.html"
}{
  "title": "[賣/桃園/面交] ASUS ROG STRIX 5700XT",
  "url": "https://www.ptt.cc/bbs/HardwareSale/M.1762240013.A.BB5.html"
}{
  "title": "[徵/全國/寄送] AMD R5 2400G ",
  "url": "https://www.ptt.cc/bbs/HardwareSale/M.1762240845.A.384.html"
}{
  "title": "[徵/台中/皆可] 徵一顆i7-6700或7700 ",
  "url": "https://www.ptt.cc/bbs/HardwareSale/M.1762245629.A.30B.html"
}