{
  "title": "[賣//] ［賣/竹苗/面交］",
  "url": "https://www.ptt.cc/bbs/HardwareSale/M.1748153428.A.FD2.html"
}{
  "title": "[賣/竹苗/面交] Benq GW2470ML護眼螢幕",
  "url": "https://www.ptt.cc/bbs/HardwareSale/M.1748153939.A.AE8.html"
}{
  "title": "[賣/新北/皆可]  GTX1650 喬斯伯C2 機殼",
  "url": "https://www.ptt.cc/bbs/HardwareSale/M.1748155803.A.025.html"
}{
  "title": "[賣/台中/皆可] D-Link 16port交換器 DGS-1016C",
  "url": "https://www.ptt.cc/bbs/HardwareSale/M.1748156435.A.7A4.html"
}{
  "title": "[賣/高雄/皆可] i7-6700+M2.512G",
  "url": "https://www.ptt.cc/bbs/HardwareSale/M.1748156957.A.60F.html"
}{
  "title": "[賣/全國/皆可] i7 9700/1060/1650/3060ti",
  "url": "https://www.ptt.cc/bbs/HardwareSale/M.1748157725.A.681.html"
}{
  "title": "[賣/台中/皆可] AC86u/google tv 4k",
  "url": "https://www.ptt.cc/bbs/HardwareSale/M.1748161090.A.6C1.html"
}{
  "title": "[賣/台北/面交] MSI RTX5070",
  "url": "https://www.ptt.cc/bbs/HardwareSale/M.1748162911.A.989.html"
}{
  "title": "[賣/全台/皆可] 酷碼 cooler master NCORE 100 M",
  "url": "https://www.ptt.cc/bbs/HardwareSale/M.1748163477.A.54A.html"
}{
  "title": "[賣/全國/皆可] 美光 Ballistix DDR4-3200 8G*2 ",
  "url": "https://www.ptt.cc/bbs/HardwareSale/M.1748164028.A.F73.html"
}{
  "title": "[賣/雙北/面交] BenQ ScreenBar Halo",
  "url": "https://www.ptt.cc/bbs/HardwareSale/M.1748164503.A.CB6.html"
}{
  "title": "[賣/桃園/皆可]3950X C8E FURY 16*2 Xtreem ",
  "url": "https://www.ptt.cc/bbs/HardwareSale/M.1748165394.A.D35.html"
}{
  "title": "[賣/雙北/面交] X670E 記憶體電供機殼一體水冷",
  "url": "https://www.ptt.cc/bbs/HardwareSale/M.1748166350.A.E1D.html"
}{
  "title": "[估價] 5900x 3070 itx",
  "url": "https://www.ptt.cc/bbs/HardwareSale/M.1748166485.A.665.html"
}{
  "title": "[賣/台北/自取] ADATA 威剛 DDR5 32GBx2 16GB*4",
  "url": "https://www.ptt.cc/bbs/HardwareSale/M.1748166900.A.23A.html"
}{
  "title": "[賣/台北/面交] JBL 104BT 電腦喇叭",
  "url": "https://www.ptt.cc/bbs/HardwareSale/M.1748167019.A.B87.html"
}{
  "title": "[徵/全國/皆可] 3.5吋 4T WD紫標硬碟",
  "url": "https://www.ptt.cc/bbs/HardwareSale/M.1748102128.A.F72.html"
}{
  "title": "[徵/雙北/面交] 650w~750w PSU 已收到 ",
  "url": "https://www.ptt.cc/bbs/HardwareSale/M.1748104366.A.C6F.html"
}{
  "title": "[賣/全國/皆可]WD SN850X 2T/Logitech G502X RMA",
  "url": "https://www.ptt.cc/bbs/HardwareSale/M.1748105133.A.B1B.html"
}{
  "title": "[賣/台北/皆可] SanDisk E30 1TB 行動固態硬碟 ",
  "url": "https://www.ptt.cc/bbs/HardwareSale/M.1748105761.A.131.html"
}{
  "title": "[賣/雙北/面交] i5 13500+B760+850w電源+4070s",
  "url": "https://www.ptt.cc/bbs/HardwareSale/M.1748107554.A.9AB.html"
}{
  "title": "[賣/全國/皆可] 12700K、Z690-E主機板、1660S顯卡、記憶體及零組件]",
  "url": "https://www.ptt.cc/bbs/HardwareSale/M.1748117530.A.975.html"
}{
  "title": "[賣/台中/皆可] 華碩Proart4080s 7800X3D B650M",
  "url": "https://www.ptt.cc/bbs/HardwareSale/M.1748118290.A.568.html"
}{
  "title": "[賣/雙北/ 皆可] 已售出 DELL 10100 SFF主機*2",
  "url": "https://www.ptt.cc/bbs/HardwareSale/M.1748138033.A.5A5.html"
}{
  "title": "[賣/板橋/面交] ASUS TUF 4070ti",
  "url": "https://www.ptt.cc/bbs/HardwareSale/M.1748139267.A.F0C.html"
}{
  "title": "[賣/雙北/皆可] RTX 3060 FC140 塔扇 R5 記憶體",
  "url": "https://www.ptt.cc/bbs/HardwareSale/M.1748142315.A.D21.html"
}{
  "title": "[徵/高雄/皆可] DDR4 3600 64g(32g*2) 一組 ",
  "url": "https://www.ptt.cc/bbs/HardwareSale/M.1748142949.A.DF7.html"
}{
  "title": "[賣/台南/皆可] i5-10400 + MSI B460M MOTAR",
  "url": "https://www.ptt.cc/bbs/HardwareSale/M.1748143084.A.66E.html"
}{
  "title": "[賣/全國/皆可]V1300W/GT1300W/RTX 3070 ",
  "url": "https://www.ptt.cc/bbs/HardwareSale/M.1748144715.A.EF8.html"
}{
  "title": "[賣/高雄/面交] I7-6700主機",
  "url": "https://www.ptt.cc/bbs/HardwareSale/M.1748145253.A.321.html"
}{
  "title": "[賣/雙北/皆可] 4080s.i9-12900KF.M2 SSD 4T ",
  "url": "https://www.ptt.cc/bbs/HardwareSale/M.1748146306.A.ADD.html"
}{
  "title": "[賣/新竹/面交] r5 3600 2070主機 aoc c27g1",
  "url": "https://www.ptt.cc/bbs/HardwareSale/M.1748146787.A.12B.html"
}{
  "title": "[賣/台北/皆可] ASUS DUAL-RTX3060TI-O8G-MINI-V",
  "url": "https://www.ptt.cc/bbs/HardwareSale/M.1748146921.A.C36.html"
}{
  "title": "[徵/台中/皆可] GTX 1650、hyper 622 212塔散",
  "url": "https://www.ptt.cc/bbs/HardwareSale/M.1748150432.A.521.html"
}{
  "title": "[徵/全國/皆可]steelseries arctis gamebuds ",
  "url": "https://www.ptt.cc/bbs/HardwareSale/M.1748150513.A.57D.html"
}{
  "title": "[徵/新北/皆可] DDR5 6000 RGB 16gx2",
  "url": "https://www.ptt.cc/bbs/HardwareSale/M.1748153044.A.576.html"
}{
  "title": "[徵/全國/皆可] 利民120系列 需有1151扣具",
  "url": "https://www.ptt.cc/bbs/HardwareSale/M.1748083979.A.D6A.html"
}{
  "title": "[賣//] [賣/新竹/皆可］技嘉 RTX 5070 EAGLE OC",
  "url": "https://www.ptt.cc/bbs/HardwareSale/M.1748084890.A.F46.html"
}{
  "title": "[賣/台北/面交] Synology DS716+",
  "url": "https://www.ptt.cc/bbs/HardwareSale/M.1748085005.A.EEC.html"
}{
  "title": "[賣/台北/皆可] MSI 1660ti 6G",
  "url": "https://www.ptt.cc/bbs/HardwareSale/M.1748085222.A.505.html"
}{
  "title": "[賣/全國/皆可] i5-6400 + h110主機板",
  "url": "https://www.ptt.cc/bbs/HardwareSale/M.1748085793.A.76D.html"
}{
  "title": "[賣/高雄/面交]RTX2060/I7-8700/DDR4 ",
  "url": "https://www.ptt.cc/bbs/HardwareSale/M.1748086355.A.3B3.html"
}{
  "title": "[賣/新北/皆可] GTX1060 Aero 3g",
  "url": "https://www.ptt.cc/bbs/HardwareSale/M.1748087605.A.63D.html"
}{
  "title": "[賣/中壢/皆可] 金士頓DDR4 3200 16G*4",
  "url": "https://www.ptt.cc/bbs/HardwareSale/M.1748088376.A.B70.html"
}{
  "title": "[賣/全國/皆可] 威剛 DDR5-4800 16GB PC",
  "url": "https://www.ptt.cc/bbs/HardwareSale/M.1748090462.A.C34.html"
}{
  "title": "[徵/全國/皆可]全套主機",
  "url": "https://www.ptt.cc/bbs/HardwareSale/M.1748090642.A.E00.html"
}{
  "title": "[賣/新北/面交] MSI RTX4070Ti Gaming12G(已售出)",
  "url": "https://www.ptt.cc/bbs/HardwareSale/M.1748091304.A.1B9.html"
}{
  "title": "[賣/台北/皆可] RTX4070Ti Gaming 12G 白卡",
  "url": "https://www.ptt.cc/bbs/HardwareSale/M.1748091662.A.EA6.html"
}{
  "title": "[賣/雙北/寄送] AMD 5900X 10G網路卡 DDR4記憶體",
  "url": "https://www.ptt.cc/bbs/HardwareSale/M.1748091861.A.050.html"
}{
  "title": "[賣/台南/皆可] 500G SSD",
  "url": "https://www.ptt.cc/bbs/HardwareSale/M.1748092000.A.8AC.html"
}{
  "title": "[賣/台中/皆可] 半套AMD R9 3900+Gigabyte B450m",
  "url": "https://www.ptt.cc/bbs/HardwareSale/M.1748092552.A.28E.html"
}{
  "title": "[賣/新竹/皆可] PC-Q37/幻光戟3200-C14 32G ",
  "url": "https://www.ptt.cc/bbs/HardwareSale/M.1748094867.A.152.html"
}{
  "title": "[賣/全國/皆可] Hyper TX3 evo 塔扇(AM4可用)",
  "url": "https://www.ptt.cc/bbs/HardwareSale/M.1748095809.A.77B.html"
}{
  "title": "[徵/雙北/面交] 27吋文書用螢幕",
  "url": "https://www.ptt.cc/bbs/HardwareSale/M.1748095941.A.449.html"
}{
  "title": "[賣/桃園/皆可]9900K ROG Z390I SFX 750W ",
  "url": "https://www.ptt.cc/bbs/HardwareSale/M.1748097471.A.431.html"
}{
  "title": "[賣/高雄/皆可] 利民 PS120 SE/ATK X1 滑鼠",
  "url": "https://www.ptt.cc/bbs/HardwareSale/M.1748097999.A.EAB.html"
}