{
  "title": "[賣/北市/皆可] RTX3070, DDR4 16G",
  "url": "https://www.ptt.cc/bbs/HardwareSale/M.1755828713.A.6F5.html"
}{
  "title": "[徵/台中/皆可] i5-9400+主機板半套",
  "url": "https://www.ptt.cc/bbs/HardwareSale/M.1755829420.A.AB4.html"
}{
  "title": "[徵/全國/寄送] 美光 MX500 500G ",
  "url": "https://www.ptt.cc/bbs/HardwareSale/M.1755829520.A.23A.html"
}{
  "title": "[賣/台南/面交] R9-9900X主機 ",
  "url": "https://www.ptt.cc/bbs/HardwareSale/M.1755830045.A.191.html"
}{
  "title": "[賣/新北/皆可] (售出）klevv ddr4 3200 8g/psu 400w",
  "url": "https://www.ptt.cc/bbs/HardwareSale/M.1755832358.A.757.html"
}{
  "title": "[賣/桃園/面交] GIGABYTE RX6600 EAGLE 8G  已售",
  "url": "https://www.ptt.cc/bbs/HardwareSale/M.1755836053.A.C4A.html"
}{
  "title": "[估價] 7700/4070tiS",
  "url": "https://www.ptt.cc/bbs/HardwareSale/M.1755837943.A.790.html"
}{
  "title": "[賣/台南/皆可] 分享器 TP-Link Archer AX73",
  "url": "https://www.ptt.cc/bbs/HardwareSale/M.1755838735.A.6EC.html"
}{
  "title": "[徵/中壢/面交] 22 ~ 24吋螢幕(已徵到)",
  "url": "https://www.ptt.cc/bbs/HardwareSale/M.1755839193.A.003.html"
}{
  "title": "[賣/全國/皆可]美光 DDR4-3200 16G*2 ",
  "url": "https://www.ptt.cc/bbs/HardwareSale/M.1755842333.A.D37.html"
}{
  "title": "[徵/高雄/面交]價位1~2000顯卡 ",
  "url": "https://www.ptt.cc/bbs/HardwareSale/M.1755848026.A.EA5.html"
}{
  "title": "[賣/全國/皆可] 顯示卡 微星4070S 風扇 塔散熱器",
  "url": "https://www.ptt.cc/bbs/HardwareSale/M.1755850577.A.E80.html"
}{
  "title": "[賣/台中/面交]ROG 2080s /EVGA 1000w GT ",
  "url": "https://www.ptt.cc/bbs/HardwareSale/M.1755850979.A.710.html"
}{
  "title": "[徵/全國/皆可] 27-32的螢幕",
  "url": "https://www.ptt.cc/bbs/HardwareSale/M.1755852060.A.EC0.html"
}{
  "title": "[賣/台南/面交] PNY5080/Enermax850金牌",
  "url": "https://www.ptt.cc/bbs/HardwareSale/M.1755852142.A.024.html"
}{
  "title": "[賣/全國/皆可] i7-9700K，硬碟，顯示卡",
  "url": "https://www.ptt.cc/bbs/HardwareSale/M.1755764019.A.1DC.html"
}{
  "title": "[賣/全國/皆可] 華碩 GT-640 2G 顯卡 ",
  "url": "https://www.ptt.cc/bbs/HardwareSale/M.1755767600.A.B23.html"
}{
  "title": "[賣/全國/皆可] Aruba AP-515 wifi 螢幕支架",
  "url": "https://www.ptt.cc/bbs/HardwareSale/M.1755770334.A.1F3.html"
}{
  "title": "[賣/北桃/皆可] 七代半套/Z490鋼鐵傳奇/鍵盤 ",
  "url": "https://www.ptt.cc/bbs/HardwareSale/M.1755771348.A.048.html"
}{
  "title": "[賣/全國/寄送]12400 + MB + RAM 半套 ",
  "url": "https://www.ptt.cc/bbs/HardwareSale/M.1755775111.A.B06.html"
}{
  "title": "[賣/桃園/賣貨便] ROG水冷/Acer記憶體/磁吸風扇",
  "url": "https://www.ptt.cc/bbs/HardwareSale/M.1755778780.A.692.html"
}{
  "title": "[賣/嘉義/皆可] Creative T100(售出)",
  "url": "https://www.ptt.cc/bbs/HardwareSale/M.1755779645.A.CB6.html"
}{
  "title": "[賣/台南/皆可] iTX機殼 有線&無線網卡 指紋辨識器",
  "url": "https://www.ptt.cc/bbs/HardwareSale/M.1755783137.A.0F0.html"
}{
  "title": "[賣/桃園/皆可] CPU I7-4790 I5-8500 512G SSD ",
  "url": "https://www.ptt.cc/bbs/HardwareSale/M.1755783265.A.E73.html"
}{
  "title": "[徵/台北/皆可] R5 5600或5600g半套 ",
  "url": "https://www.ptt.cc/bbs/HardwareSale/M.1755784065.A.156.html"
}{
  "title": "[賣/雙北/皆可] (暫售)Intel Arc A750",
  "url": "https://www.ptt.cc/bbs/HardwareSale/M.1755785490.A.612.html"
}{
  "title": "[賣/台北/面交] 華碩 TUF 3070ti顯卡",
  "url": "https://www.ptt.cc/bbs/HardwareSale/M.1755786493.A.DD3.html"
}{
  "title": "[徵/全國/皆可]synology wrx60 或 rt6600ax ",
  "url": "https://www.ptt.cc/bbs/HardwareSale/M.1755788077.A.BAE.html"
}{
  "title": "[賣/彰化/皆可] 華碩1050ti 4g bx500 1t ddr4 8g",
  "url": "https://www.ptt.cc/bbs/HardwareSale/M.1755789152.A.639.html"
}{
  "title": "[徵/彰化/皆可] 液晶螢幕 各種尺寸皆可",
  "url": "https://www.ptt.cc/bbs/HardwareSale/M.1755791251.A.DFE.html"
}{
  "title": "[賣/全國/皆可] 致動 超級傳奇霍爾手把",
  "url": "https://www.ptt.cc/bbs/HardwareSale/M.1755792536.A.AFB.html"
}{
  "title": "[賣/北市/皆可] 海韻PSU Prime TX-750 ",
  "url": "https://www.ptt.cc/bbs/HardwareSale/M.1755796565.A.54F.html"
}{
  "title": "[賣/雙北/面交]故障MSI RX580 8G ",
  "url": "https://www.ptt.cc/bbs/HardwareSale/M.1755818326.A.E81.html"
}{
  "title": "[徵/全國/寄送] SATA SSD 256G or 240G",
  "url": "https://www.ptt.cc/bbs/HardwareSale/M.1755822064.A.266.html"
}{
  "title": "[徵/台北/皆可] 徵張rx6800",
  "url": "https://www.ptt.cc/bbs/HardwareSale/M.1755823456.A.B18.html"
}{
  "title": "[徵/台北/皆可] 分體水冷240mm水冷排 ",
  "url": "https://www.ptt.cc/bbs/HardwareSale/M.1755738923.A.DD2.html"
}{
  "title": "[徵/新竹/面交] 3060ti 顯示卡 ",
  "url": "https://www.ptt.cc/bbs/HardwareSale/M.1755738976.A.8E7.html"
}{
  "title": "[賣/彰化/皆可]AMD Ryzen R9 3900X",
  "url": "https://www.ptt.cc/bbs/HardwareSale/M.1755739361.A.8BB.html"
}{
  "title": "[賣/台中/面交] 售出 3700X+3060ti 主機",
  "url": "https://www.ptt.cc/bbs/HardwareSale/M.1755740897.A.F1C.html"
}{
  "title": "[賣/新竹/皆可] asus rx9060 xt  8g",
  "url": "https://www.ptt.cc/bbs/HardwareSale/M.1755743138.A.5EA.html"
}{
  "title": "[賣/全國/皆可] 大量 DDR5,4,3,網卡,M.2SSD",
  "url": "https://www.ptt.cc/bbs/HardwareSale/M.1755743248.A.06C.html"
}{
  "title": "[賣/全國/寄送] (售出)APC BR1000G-TW 1000VA UP",
  "url": "https://www.ptt.cc/bbs/HardwareSale/M.1755747526.A.E9B.html"
}{
  "title": "[賣/全國/皆可] DDR4幻光戟16G CL14",
  "url": "https://www.ptt.cc/bbs/HardwareSale/M.1755748658.A.123.html"
}{
  "title": "[賣/全台/寄貨] LIAN LI ST12O風扇組 argb風扇3入",
  "url": "https://www.ptt.cc/bbs/HardwareSale/M.1755749103.A.A4B.html"
}{
  "title": "[賣/台北/面交] 全漢 FSP CST-320 靜化論 機殼",
  "url": "https://www.ptt.cc/bbs/HardwareSale/M.1755754756.A.488.html"
}{
  "title": "[賣/台北/皆可] 4070S/海韻1000W/小米AX3000T",
  "url": "https://www.ptt.cc/bbs/HardwareSale/M.1755756044.A.AFF.html"
}{
  "title": "[賣/台北/面交]金士頓SODIMM 8GB DDR3 1600 RAM ",
  "url": "https://www.ptt.cc/bbs/HardwareSale/M.1755757544.A.E46.html"
}{
  "title": "[賣/桃園/面交]  技嘉 RTX 5050 OC 8G 3風扇",
  "url": "https://www.ptt.cc/bbs/HardwareSale/M.1755760202.A.37F.html"
}{
  "title": "[賣/楊梅/皆可] 美光DDR4 8G*2 16G 2666 記憶體",
  "url": "https://www.ptt.cc/bbs/HardwareSale/M.1755760669.A.05A.html"
}{
  "title": "[賣/新竹/皆可] R7-3700X+3060Ti主機",
  "url": "https://www.ptt.cc/bbs/HardwareSale/M.1755761414.A.268.html"
}{
  "title": "[賣/全國/皆可]RX570-4G+R7-250(故障) ",
  "url": "https://www.ptt.cc/bbs/HardwareSale/M.1755762025.A.C76.html"
}